LICENSE
MANIFEST.in
README.md
setup.py
request_tack_id/__init__.py
request_tack_id/__version__.py
request_tack_id/filters.py
request_tack_id/middleware.py
request_tack_id/tests.py
request_tack_id.egg-info/PKG-INFO
request_tack_id.egg-info/SOURCES.txt
request_tack_id.egg-info/dependency_links.txt
request_tack_id.egg-info/top_level.txt
testproject/__init__.py
testproject/handler.py
testproject/settings.py
testproject/urls.py
testproject/views.py