Metadata-Version: 2.1
Name: request-tack-id
Version: 0.0.1
Summary: My short description for my project.
Home-page: https://github.com/DYL521/request_id
Author: DYL521
Author-email: 1016068291@qq.com
License: MIT
Platform: UNKNOWN
Classifier: License :: OSI Approved :: MIT License
Classifier: Programming Language :: Python
Classifier: Programming Language :: Python :: 3
Classifier: Programming Language :: Python :: 3.6
Classifier: Programming Language :: Python :: Implementation :: CPython
Classifier: Programming Language :: Python :: Implementation :: PyPy
Requires-Python: >=3.6.0
